linak_controller/__init__.py
linak_controller/config.py
linak_controller/desk.py
linak_controller/gatt.py
linak_controller/main.py
linak_controller/util.py
linak_controller/example/config.yaml
linak_controller-1.3.2.dist-info/METADATA
linak_controller-1.3.2.dist-info/WHEEL
linak_controller-1.3.2.dist-info/entry_points.txt
linak_controller-1.3.2.dist-info/licenses/LICENSE
linak_controller-1.3.2.dist-info/RECORD
