Metadata-Version: 2.4
Name: linak-controller
Version: 1.3.2
Summary: Command line tool for controlling the Linak standing desks
Author: Rhys Tyers
License-Expression: MIT
License-File: LICENSE
Requires-Python: >=3.9
Requires-Dist: aiohttp<4,>=3.8.4
Requires-Dist: appdirs<2,>=1.4.4
Requires-Dist: bleak<2,>=1.1.1
Requires-Dist: pyyaml~=6.0
